<?xml version="1.0" encoding="UTF-8"?>
<comment version="3.0">
  <caption>a top view hot espresso with brown coffee seeds on the brown wooden desk coffee cup drink</caption>
  <note>a top view hot espresso with brown coffee seeds on the brown wooden desk coffee cup drink</note>
  <place/>
  <categories>
    <category value="wooden"/>
    <category value="view"/>
    <category value="top"/>
    <category value="seeds"/>
    <category value="saucer"/>
    <category value="mug"/>
    <category value="morning"/>
    <category value="hot espresso"/>
    <category value="hot"/>
    <category value="food"/>
    <category value="espresso"/>
    <category value="drink"/>
    <category value="desk"/>
    <category value="cup"/>
    <category value="coffee"/>
    <category value="cappuccino"/>
    <category value="caffeine"/>
    <category value="brown"/>
    <category value="breakfast"/>
    <category value="beverage"/>
    <category value="aroma"/>
  </categories>
</comment>
